awesome_streamlit/__init__.py
awesome_streamlit_master-20200130.3.dist-info/METADATA
awesome_streamlit_master-20200130.3.dist-info/WHEEL
awesome_streamlit_master-20200130.3.dist-info/top_level.txt
awesome_streamlit_master-20200130.3.dist-info/RECORD
